jala/__init__.py
jala/app.py
jala/middleware.py
jala/response.py
jala-0.1.4.dist-info/METADATA
jala-0.1.4.dist-info/WHEEL
jala-0.1.4.dist-info/top_level.txt
jala-0.1.4.dist-info/RECORD
