Metadata-Version: 2.1
Name: jala
Version: 0.1.4
Summary: Python Web Framework built for learning purpose
Home-page: https://github.com/Ikromjon0102/jala
Author: Ikromjon Ergashev
Author-email: ikromjon01021995@gmail.com
License: MIT
Platform: UNKNOWN
Classifier: License :: OSI Approved :: MIT License
Classifier: Programming Language :: Python
Classifier: Programming Language :: Python :: 3
Classifier: Programming Language :: Python :: 3.6
Classifier: Programming Language :: Python :: Implementation :: CPython
Classifier: Programming Language :: Python :: Implementation :: PyPy
Requires-Python: >=3.9.0
Requires-Dist: jinja2==3.1.4
Requires-Dist: WebOb==1.8.9
Requires-Dist: whitenoise==6.8.2
Requires-Dist: parse==1.20.2
Requires-Dist: requests-wsgi-adapter==0.4.1
Requires-Dist: requests==2.32.3
